uart_tx.v
module uart_tx(
    input clk,
    input rst,
    input tx_start,
    input [7:0] data_in,
    output reg tx,
    output reg busy
);

reg [1:0] state;
reg [2:0] bit_count;
reg [7:0] data_reg;

parameter IDLE  = 2'b00;
parameter START = 2'b01;
parameter DATA  = 2'b10;
parameter STOP  = 2'b11;

always @(posedge clk or posedge rst)
begin
    if(rst)
    begin
        state <= IDLE;
        tx <= 1'b1;
        busy <= 1'b0;
        bit_count <= 0;
    end
    else
    begin
        case(state)

        IDLE:
        begin
            tx <= 1'b1;
            busy <= 1'b0;

            if(tx_start)
            begin
                data_reg <= data_in;
                state <= START;
                busy <= 1'b1;
            end
        end

        START:
        begin
            tx <= 1'b0;
            bit_count <= 0;
            state <= DATA;
        end

        DATA:
        begin
            tx <= data_reg[bit_count];

            if(bit_count == 7)
                state <= STOP;
            else
                bit_count <= bit_count + 1;
        end

        STOP:
        begin
            tx <= 1'b1;
            state <= IDLE;
        end

        endcase
    end
end

endmodule

tb_uart_tx.v
module tb_uart_tx;

reg clk;
reg rst;
reg tx_start;
reg [7:0] data_in;

wire tx;
wire busy;

uart_tx uut(
    .clk(clk),
    .rst(rst),
    .tx_start(tx_start),
    .data_in(data_in),
    .tx(tx),
    .busy(busy)
);

always #5 clk = ~clk;

initial
begin
    clk = 0;
    rst = 1;
    tx_start = 0;
    data_in = 8'b10110011;

    #10 rst = 0;

    #10;
    tx_start = 1;

    #10;
    tx_start = 0;

    #150;
    $finish;
end

initial
begin
    $dumpfile("uart_tx.vcd");
    $dumpvars(0,tb_uart_tx);
end

endmodule

uart_tx.vcd
$date
	Wed Jun 10 10:33:17 2026
$end
$version
	Icarus Verilog
$end
$timescale
	1s
$end
$scope module tb_uart_tx $end
$var wire 1 ! tx $end
$var wire 1 " busy $end
$var reg 1 # clk $end
$var reg 8 $ data_in [7:0] $end
$var reg 1 % rst $end
$var reg 1 & tx_start $end
$scope module uut $end
$var wire 1 # clk $end
$var wire 8 ' data_in [7:0] $end
$var wire 1 % rst $end
$var wire 1 & tx_start $end
$var reg 3 ( bit_count [2:0] $end
$var reg 1 " busy $end
$var reg 8 ) data_reg [7:0] $end
$var reg 2 * state [1:0] $end
$var reg 1 ! tx $end
$upscope $end
$upscope $end
$enddefinitions $end
#0
$dumpvars
b0 *
bx )
b0 (
b10110011 '
0&
1%
b10110011 $
0#
0"
1!
$end
#5
1#
#10
0#
0%
#15
1#
#20
0#
1&
#25
1"
b1 *
b10110011 )
1#
#30
0#
0&
#35
b10 *
0!
1#
#40
0#
#45
b1 (
1!
1#
#50
0#
#55
b10 (
1#
#60
0#
#65
b11 (
0!
1#
#70
0#
#75
b100 (
1#
#80
0#
#85
b101 (
1!
1#
#90
0#
#95
b110 (
1#
#100
0#
#105
b111 (
0!
1#
#110
0#
#115
b11 *
1!
1#
#120
0#
#125
b0 *
1#
#130
0#
#135
0"
1#
